Voice_Shifter/voice_corruptor/pulse_gen.sv
module pulse_gen (
    input logic clk,
    input logic flag,
    output logic pulse
);

    typedef enum {IDLE, PULSE, WAIT_LOW} mystate;
    mystate c_state, n_state;

    always_ff @(posedge clk) begin
        c_state <= n_state;
    end

    always_comb begin
        pulse   = 1'b0;
        n_state = c_state;
        case (c_state)
            IDLE: begin
                if (flag)
                    n_state = PULSE;
            end
            PULSE: begin
                pulse = 1'b1;
                n_state = WAIT_LOW;
            end
            WAIT_LOW: begin
                pulse = 1'b0;
                if(!flag)
                    n_state = IDLE;
                else
                    n_state = WAIT_LOW;
            end
        endcase
    end
endmodule

Voice_Shifter/voice_corruptor/down_counter.sv
module down_counter #(
    parameter int WIDTH = 9
)(
    input logic clk,
    input logic rst,
    input logic en,
    input logic reload_flag1,
    input logic reload_flag2,
    input logic [WIDTH-1:0] max_count,
    input logic [WIDTH-1:0] init,
    output logic [WIDTH-1:0] count
);

    logic [WIDTH-1:0] counting;
    logic decrement;
    logic down;
    logic reload1, reload2;

    pulse_gen down_pulse (
        .clk(clk),
        .flag(en),
        .pulse(down)
    );

    pulse_gen reload1_pulse (
        .clk(clk),
        .flag(reload_flag1),
        .pulse(reload1)
    );

    pulse_gen reload2_pulse (
        .clk(clk),
        .flag(reload_flag2),
        .pulse(reload2)
    );

    always_ff @(posedge clk or posedge rst) begin
        if (rst || reload2 || reload1)
            decrement <= 1'b0;
        else if (down)
            decrement <= ~decrement;
    end

    always_ff @(posedge clk or posedge rst) begin
        if (rst || reload2) begin
            counting <= init;
        end else if (reload1) begin
            counting <= max_count;
        end else if (counting == 0)
            counting <= 0;
        else if (en)
            counting <= counting - decrement;
    end


    assign count = counting;

endmodule

Voice_Shifter/voice_corruptor/testbenches/down_counter_tb.sv
`timescale 1ns/1ns

module down_counter_tb;
    localparam int CLK_PERIOD = 2;
    localparam int EN_PERIOD  = 5;    // en high 1 cycle, low 4
    localparam int RELOAD_EVERY = 50; // 7 enables * 5 clocks
    localparam logic [8:0] INIT = 9'd7;
    localparam logic [8:0] MAX_COUNT = 9'd10;

    logic clk = 1'b0;
    logic rst = 1'b1;
    logic en;
    logic reload_flag1;
    logic reload_flag2;
    logic [8:0] count;
    logic [8:0] init, max_count;

    assign init = INIT;
    assign max_count = MAX_COUNT;

    down_counter #(.WIDTH(9)) uut (
        .clk   (clk),
        .rst   (rst),
        .en    (en),
        .reload_flag1(reload_flag1),
        .reload_flag2(reload_flag2),
        .init  (init),
        .max_count(max_count),
        .count (count)
    );

    always #(CLK_PERIOD/2) clk = ~clk;

    // Wide enough for any RELOAD_EVERY. [5:0] only goes to 63, so a
    // period of 70 never matches (RELOAD_EVERY-1) and frame never advances.
    int tick;
    int frame;

    always_ff @(posedge clk) begin
        if (rst) begin
            tick  <= 0;
            frame <= 0;
        end else if (tick == RELOAD_EVERY - 1) begin
            tick  <= 0;
            frame <= frame + 1;
        end else begin
            tick <= tick + 1;
        end
    end

    // en is 1 on ticks 4, 9, 14, 19, 24, 29, 34  →  seven 1-cycle pulses
    // in each 35-cycle frame, then 4 lows before the next.
    assign en = (!rst && (tick % EN_PERIOD == EN_PERIOD - 1));

    // reload_flag:
    //   frame 0: none (rst already loaded init)
    //   frame 1: 1-cycle pulse at tick==0
    //   frame 2: held high for 8 cycles  ← long-flag test
    //   frame 3+: 1-cycle pulse again
    // Both flags default 0. A held-high flag2 (the old default) never
    // releases pulse_gen, so the next 1-cycle flag2 is ignored.
    //   frame 0: no reload (rst already loaded init)
    //   frame 1: 1-cycle flag2 at tick 0  → reload to init
    //   frame 2: flag1 held 8 cycles      → one pulse, reload to max
    //   frame 3,4: 1-cycle flag1 at tick 0
    //   frame 5+: 1-cycle flag2 at tick 0
    always_comb begin
        reload_flag1 = 1'b0;
        reload_flag2 = 1'b0;
        if (!rst && frame != 0) begin
            if (frame == 2)
                reload_flag1 = (tick <= 7);
            else if (frame == 3 || frame == 4)
                reload_flag1 = (tick == 0);
            else if (frame == 1 || frame >= 5)
                reload_flag2 = (tick == 0);
        end
    end

    initial begin
        $dumpfile("down_counter_tb.vcd");
        $dumpvars(0, down_counter_tb);

        $display("time\trst\ten\tflag1\tflag2\treload1\treload2\tcount\tframe\ttick");
        $display("----\t---\t--\t-----\t-----\t-------\t-------\t-----\t-----\t----");

        rst = 1'b1;
        repeat (4) @(posedge clk);
        @(negedge clk);
        rst = 1'b0;

        // frame 0 count, 1 init-reload, 2 long max-reload, 3-4 max, 5+ init
        wait (frame == 6);
        @(posedge clk);
        $display("done.");
        $finish;
    end

    // $strobe prints AFTER nonblocking updates, so count is the new value.
    always @(posedge clk) begin
        if (rst || en || reload_flag1 || reload_flag2)
            $strobe("%0t\t%b\t%b\t%b\t%b\t%b\t%b\t%0d\t%0d\t%0d",
                    $time, rst, en, reload_flag1, reload_flag2,
                    uut.reload1, uut.reload2, count, frame, tick);
    end
endmodule

Voice_Shifter/voice_corruptor/testbenches/down_counter_tb.vcd
$date
	Sat Aug 29 13:10:23 2026
$end
$version
	Icarus Verilog
$end
$timescale
	1ns
$end
$scope module down_counter_tb $end
$var wire 1 ! en $end
$var wire 9 " init [8:0] $end
$var wire 9 # max_count [8:0] $end
$var wire 9 $ count [8:0] $end
$var parameter 32 % CLK_PERIOD $end
$var parameter 32 & EN_PERIOD $end
$var parameter 9 ' INIT $end
$var parameter 9 ( MAX_COUNT $end
$var parameter 32 ) RELOAD_EVERY $end
$var reg 1 * clk $end
$var reg 1 + reload_flag1 $end
$var reg 1 , reload_flag2 $end
$var reg 1 - rst $end
$var integer 32 . frame [31:0] $end
$var integer 32 / tick [31:0] $end
$scope module uut $end
$var wire 1 * clk $end
$var wire 9 0 count [8:0] $end
$var wire 1 ! en $end
$var wire 9 1 init [8:0] $end
$var wire 9 2 max_count [8:0] $end
$var wire 1 + reload_flag1 $end
$var wire 1 , reload_flag2 $end
$var wire 1 - rst $end
$var wire 1 3 reload2 $end
$var wire 1 4 reload1 $end
$var wire 1 5 down $end
$var parameter 32 6 WIDTH $end
$var reg 9 7 counting [8:0] $end
$var reg 1 8 decrement $end
$scope module down_pulse $end
$var wire 1 * clk $end
$var wire 1 ! flag $end
$var reg 1 5 pulse $end
$var integer 32 9 c_state [31:0] $end
$var integer 32 : n_state [31:0] $end
$upscope $end
$scope module reload1_pulse $end
$var wire 1 * clk $end
$var wire 1 + flag $end
$var reg 1 4 pulse $end
$var integer 32 ; c_state [31:0] $end
$var integer 32 < n_state [31:0] $end
$upscope $end
$scope module reload2_pulse $end
$var wire 1 * clk $end
$var wire 1 , flag $end
$var reg 1 3 pulse $end
$var integer 32 = c_state [31:0] $end
$var integer 32 > n_state [31:0] $end
$upscope $end
$upscope $end
$upscope $end
$enddefinitions $end
$comment Show the parameter values. $end
$dumpall
b1001 6
b110010 )
b1010 (
b111 '
b101 &
b10 %
$end
#0
$dumpvars
b0 >
b0 =
b0 <
b0 ;
b0 :
b0 9
x8
bx 7
05
04
03
b1010 2
b111 1
bx 0
b0 /
b0 .
1-
0,
0+
0*
bx $
b1010 #
b111 "
0!
$end
#1
08
b111 $
b111 0
b111 7
1*
#2
0*
#3
1*
#4
0*
#5
1*
#6
0*
#7
1*
#8
0-
0*
#9
b1 /
1*
#10
0*
#11
b10 /
1*
#12
0*
#13
b11 /
1*
#14
0*
#15
b1 :
1!
b100 /
1*
#16
0*
#17
b10 :
15
0!
b1 9
b101 /
1*
#18
0*
#19
b0 :
05
b110 /
b10 9
18
1*
#20
0*
#21
b0 9
b111 /
1*
#22
0*
#23
b1000 /
1*
#24
0*
#25
b1 :
1!
b1001 /
1*
#26
0*
#27
0!
b10 :
15
b1010 /
b1 9
b110 $
b110 0
b110 7
1*
#28
0*
#29
b0 :
05
b10 9
b1011 /
08
1*
#30
0*
#31
b1100 /
b0 9
1*
#32
0*
#33
b1101 /
1*
#34
0*
#35
b1 :
1!
b1110 /
1*
#36
0*
#37
b10 :
15
0!
b1 9
b1111 /
1*
#38
0*
#39
b0 :
05
b10000 /
b10 9
18
1*
#40
0*
#41
b0 9
b10001 /
1*
#42
0*
#43
b10010 /
1*
#44
0*
#45
b1 :
1!
b10011 /
1*
#46
0*
#47
0!
b10 :
15
b10100 /
b1 9
b101 $
b101 0
b101 7
1*
#48
0*
#49
b0 :
05
b10 9
b10101 /
08
1*
#50
0*
#51
b10110 /
b0 9
1*
#52
0*
#53
b10111 /
1*
#54
0*
#55
b1 :
1!
b11000 /
1*
#56
0*
#57
b10 :
15
0!
b1 9
b11001 /
1*
#58
0*
#59
b0 :
05
b11010 /
b10 9
18
1*
#60
0*
#61
b0 9
b11011 /
1*
#62
0*
#63
b11100 /
1*
#64
0*
#65
b1 :
1!
b11101 /
1*
#66
0*
#67
0!
b10 :
15
b11110 /
b1 9
b100 $
b100 0
b100 7
1*
#68
0*
#69
b0 :
05
b10 9
b11111 /
08
1*
#70
0*
#71
b100000 /
b0 9
1*
#72
0*
#73
b100001 /
1*
#74
0*
#75
b1 :
1!
b100010 /
1*
#76
0*
#77
b10 :
15
0!
b1 9
b100011 /
1*
#78
0*
#79
b0 :
05
b100100 /
b10 9
18
1*
#80
0*
#81
b0 9
b100101 /
1*
#82
0*
#83
b100110 /
1*
#84
0*
#85
b1 :
1!
b100111 /
1*
#86
0*
#87
0!
b10 :
15
b101000 /
b1 9
b11 $
b11 0
b11 7
1*
#88
0*
#89
b0 :
05
b10 9
b101001 /
08
1*
#90
0*
#91
b101010 /
b0 9
1*
#92
0*
#93
b101011 /
1*
#94
0*
#95
b1 :
1!
b101100 /
1*
#96
0*
#97
b10 :
15
0!
b1 9
b101101 /
1*
#98
0*
#99
b0 :
05
b101110 /
b10 9
18
1*
#100
0*
#101
b0 9
b101111 /
1*
#102
0*
#103
b110000 /
1*
#104
0*
#105
b1 :
1!
b110001 /
1*
#106
0*
#107
b1 >
1,
0!
b10 :
15
b1 .
b0 /
b1 9
b10 $
b10 0
b10 7
1*
#108
0*
#109
b0 :
05
b10 >
13
0,
b10 9
b1 =
b1 /
08
1*
#110
0*
#111
b0 >
03
b10 /
b10 =
b0 9
b111 $
b111 0
b111 7
1*
#112
0*
#113
b0 =
b11 /
1*
#114
0*
#115
b1 :
1!
b100 /
1*
#116
0*
#117
b10 :
15
0!
b1 9
b101 /
1*
#118
0*
#119
b0 :
05
b110 /
b10 9
18
1*
#120
0*
#121
b0 9
b111 /
1*
#122
0*
#123
b1000 /
1*
#124
0*
#125
b1 :
1!
b1001 /
1*
#126
0*
#127
0!
b10 :
15
b1010 /
b1 9
b110 $
b110 0
b110 7
1*
#128
0*
#129
b0 :
05
b10 9
b1011 /
08
1*
#130
0*
#131
b1100 /
b0 9
1*
#132
0*
#133
b1101 /
1*
#134
0*
#135
b1 :
1!
b1110 /
1*
#136
0*
#137
b10 :
15
0!
b1 9
b1111 /
1*
#138
0*
#139
b0 :
05
b10000 /
b10 9
18
1*
#140
0*
#141
b0 9
b10001 /
1*
#142
0*
#143
b10010 /
1*
#144
0*
#145
b1 :
1!
b10011 /
1*
#146
0*
#147
0!
b10 :
15
b10100 /
b1 9
b101 $
b101 0
b101 7
1*
#148
0*
#149
b0 :
05
b10 9
b10101 /
08
1*
#150
0*
#151
b10110 /
b0 9
1*
#152
0*
#153
b10111 /
1*
#154
0*
#155
b1 :
1!
b11000 /
1*
#156
0*
#157
b10 :
15
0!
b1 9
b11001 /
1*
#158
0*
#159
b0 :
05
b11010 /
b10 9
18
1*
#160
0*
#161
b0 9
b11011 /
1*
#162
0*
#163
b11100 /
1*
#164
0*
#165
b1 :
1!
b11101 /
1*
#166
0*
#167
0!
b10 :
15
b11110 /
b1 9
b100 $
b100 0
b100 7
1*
#168
0*
#169
b0 :
05
b10 9
b11111 /
08
1*
#170
0*
#171
b100000 /
b0 9
1*
#172
0*
#173
b100001 /
1*
#174
0*
#175
b1 :
1!
b100010 /
1*
#176
0*
#177
b10 :
15
0!
b1 9
b100011 /
1*
#178
0*
#179
b0 :
05
b100100 /
b10 9
18
1*
#180
0*
#181
b0 9
b100101 /
1*
#182
0*
#183
b100110 /
1*
#184
0*
#185
b1 :
1!
b100111 /
1*
#186
0*
#187
0!
b10 :
15
b101000 /
b1 9
b11 $
b11 0
b11 7
1*
#188
0*
#189
b0 :
05
b10 9
b101001 /
08
1*
#190
0*
#191
b101010 /
b0 9
1*
#192
0*
#193
b101011 /
1*
#194
0*
#195
b1 :
1!
b101100 /
1*
#196
0*
#197
b10 :
15
0!
b1 9
b101101 /
1*
#198
0*
#199
b0 :
05
b101110 /
b10 9
18
1*
#200
0*
#201
b0 9
b101111 /
1*
#202
0*
#203
b110000 /
1*
#204
0*
#205
b1 :
1!
b110001 /
1*
#206
0*
#207
b1 <
1+
0!
b10 :
15
b10 .
b0 /
b1 9
b10 $
b10 0
b10 7
1*
#208
0*
#209
b0 :
05
b10 <
14
1+
b10 9
b1 ;
b1 /
08
1*
#210
0*
#211
1+
04
b10 /
b10 ;
b0 9
b1010 $
b1010 0
b1010 7
1*
#212
0*
#213
1+
b11 /
1*
#214
0*
#215
b1 :
1+
1!
b100 /
1*
#216
0*
#217
b10 :
15
1+
0!
b1 9
b101 /
1*
#218
0*
#219
1+
b0 :
05
b110 /
b10 9
18
1*
#220
0*
#221
1+
b0 9
b111 /
1*
#222
0*
#223
b0 <
0+
b1000 /
1*
#224
0*
#225
b1 :
1!
b0 ;
b1001 /
1*
#226
0*
#227
0!
b10 :
15
b1010 /
b1 9
b1001 $
b1001 0
b1001 7
1*
#228
0*
#229
b0 :
05
b10 9
b1011 /
08
1*
#230
0*
#231
b1100 /
b0 9
1*
#232
0*
#233
b1101 /
1*
#234
0*
#235
b1 :
1!
b1110 /
1*
#236
0*
#237
b10 :
15
0!
b1 9
b1111 /
1*
#238
0*
#239
b0 :
05
b10000 /
b10 9
18
1*
#240
0*
#241
b0 9
b10001 /
1*
#242
0*
#243
b10010 /
1*
#244
0*
#245
b1 :
1!
b10011 /
1*
#246
0*
#247
0!
b10 :
15
b10100 /
b1 9
b1000 $
b1000 0
b1000 7
1*
#248
0*
#249
b0 :
05
b10 9
b10101 /
08
1*
#250
0*
#251
b10110 /
b0 9
1*
#252
0*
#253
b10111 /
1*
#254
0*
#255
b1 :
1!
b11000 /
1*
#256
0*
#257
b10 :
15
0!
b1 9
b11001 /
1*
#258
0*
#259
b0 :
05
b11010 /
b10 9
18
1*
#260
0*
#261
b0 9
b11011 /
1*
#262
0*
#263
b11100 /
1*
#264
0*
#265
b1 :
1!
b11101 /
1*
#266
0*
#267
0!
b10 :
15
b11110 /
b1 9
b111 $
b111 0
b111 7
1*
#268
0*
#269
b0 :
05
b10 9
b11111 /
08
1*
#270
0*
#271
b100000 /
b0 9
1*
#272
0*
#273
b100001 /
1*
#274
0*
#275
b1 :
1!
b100010 /
1*
#276
0*
#277
b10 :
15
0!
b1 9
b100011 /
1*
#278
0*
#279
b0 :
05
b100100 /
b10 9
18
1*
#280
0*
#281
b0 9
b100101 /
1*
#282
0*
#283
b100110 /
1*
#284
0*
#285
b1 :
1!
b100111 /
1*
#286
0*
#287
0!
b10 :
15
b101000 /
b1 9
b110 $
b110 0
b110 7
1*
#288
0*
#289
b0 :
05
b10 9
b101001 /
08
1*
#290
0*
#291
b101010 /
b0 9
1*
#292
0*
#293
b101011 /
1*
#294
0*
#295
b1 :
1!
b101100 /
1*
#296
0*
#297
b10 :
15
0!
b1 9
b101101 /
1*
#298
0*
#299
b0 :
05
b101110 /
b10 9
18
1*
#300
0*
#301
b0 9
b101111 /
1*
#302
0*
#303
b110000 /
1*
#304
0*
#305
b1 :
1!
b110001 /
1*
#306
0*
#307
b1 <
1+
0!
b10 :
15
b11 .
b0 /
b1 9
b101 $
b101 0
b101 7
1*
#308
0*
#309
b0 :
05
b10 <
14
0+
b10 9
b1 ;
b1 /
08
1*
#310
0*
#311
b0 <
04
b10 /
b10 ;
b0 9
b1010 $
b1010 0
b1010 7
1*
#312
0*
#313
b0 ;
b11 /
1*
#314
0*
#315
b1 :
1!
b100 /
1*
#316
0*
#317
b10 :
15
0!
b1 9
b101 /
1*
#318
0*
#319
b0 :
05
b110 /
b10 9
18
1*
#320
0*
#321
b0 9
b111 /
1*
#322
0*
#323
b1000 /
1*
#324
0*
#325
b1 :
1!
b1001 /
1*
#326
0*
#327
0!
b10 :
15
b1010 /
b1 9
b1001 $
b1001 0
b1001 7
1*
#328
0*
#329
b0 :
05
b10 9
b1011 /
08
1*
#330
0*
#331
b1100 /
b0 9
1*
#332
0*
#333
b1101 /
1*
#334
0*
#335
b1 :
1!
b1110 /
1*
#336
0*
#337
b10 :
15
0!
b1 9
b1111 /
1*
#338
0*
#339
b0 :
05
b10000 /
b10 9
18
1*
#340
0*
#341
b0 9
b10001 /
1*
#342
0*
#343
b10010 /
1*
#344
0*
#345
b1 :
1!
b10011 /
1*
#346
0*
#347
0!
b10 :
15
b10100 /
b1 9
b1000 $
b1000 0
b1000 7
1*
#348
0*
#349
b0 :
05
b10 9
b10101 /
08
1*
#350
0*
#351
b10110 /
b0 9
1*
#352
0*
#353
b10111 /
1*
#354
0*
#355
b1 :
1!
b11000 /
1*
#356
0*
#357
b10 :
15
0!
b1 9
b11001 /
1*
#358
0*
#359
b0 :
05
b11010 /
b10 9
18
1*
#360
0*
#361
b0 9
b11011 /
1*
#362
0*
#363
b11100 /
1*
#364
0*
#365
b1 :
1!
b11101 /
1*
#366
0*
#367
0!
b10 :
15
b11110 /
b1 9
b111 $
b111 0
b111 7
1*
#368
0*
#369
b0 :
05
b10 9
b11111 /
08
1*
#370
0*
#371
b100000 /
b0 9
1*
#372
0*
#373
b100001 /
1*
#374
0*
#375
b1 :
1!
b100010 /
1*
#376
0*
#377
b10 :
15
0!
b1 9
b100011 /
1*
#378
0*
#379
b0 :
05
b100100 /
b10 9
18
1*
#380
0*
#381
b0 9
b100101 /
1*
#382
0*
#383
b100110 /
1*
#384
0*
#385
b1 :
1!
b100111 /
1*
#386
0*
#387
0!
b10 :
15
b101000 /
b1 9
b110 $
b110 0
b110 7
1*
#388
0*
#389
b0 :
05
b10 9
b101001 /
08
1*
#390
0*
#391
b101010 /
b0 9
1*
#392
0*
#393
b101011 /
1*
#394
0*
#395
b1 :
1!
b101100 /
1*
#396
0*
#397
b10 :
15
0!
b1 9
b101101 /
1*
#398
0*
#399
b0 :
05
b101110 /
b10 9
18
1*
#400
0*
#401
b0 9
b101111 /
1*
#402
0*
#403
b110000 /
1*
#404
0*
#405
b1 :
1!
b110001 /
1*
#406
0*
#407
b1 <
1+
0!
b10 :
15
b100 .
b0 /
b1 9
b101 $
b101 0
b101 7
1*
#408
0*
#409
b0 :
05
b10 <
14
0+
b10 9
b1 ;
b1 /
08
1*
#410
0*
#411
b0 <
04
b10 /
b10 ;
b0 9
b1010 $
b1010 0
b1010 7
1*
#412
0*
#413
b0 ;
b11 /
1*
#414
0*
#415
b1 :
1!
b100 /
1*
#416
0*
#417
b10 :
15
0!
b1 9
b101 /
1*
#418
0*
#419
b0 :
05
b110 /
b10 9
18
1*
#420
0*
#421
b0 9
b111 /
1*
#422
0*
#423
b1000 /
1*
#424
0*
#425
b1 :
1!
b1001 /
1*
#426
0*
#427
0!
b10 :
15
b1010 /
b1 9
b1001 $
b1001 0
b1001 7
1*
#428
0*
#429
b0 :
05
b10 9
b1011 /
08
1*
#430
0*
#431
b1100 /
b0 9
1*
#432
0*
#433
b1101 /
1*
#434
0*
#435
b1 :
1!
b1110 /
1*
#436
0*
#437
b10 :
15
0!
b1 9
b1111 /
1*
#438
0*
#439
b0 :
05
b10000 /
b10 9
18
1*
#440
0*
#441
b0 9
b10001 /
1*
#442
0*
#443
b10010 /
1*
#444
0*
#445
b1 :
1!
b10011 /
1*
#446
0*
#447
0!
b10 :
15
b10100 /
b1 9
b1000 $
b1000 0
b1000 7
1*
#448
0*
#449
b0 :
05
b10 9
b10101 /
08
1*
#450
0*
#451
b10110 /
b0 9
1*
#452
0*
#453
b10111 /
1*
#454
0*
#455
b1 :
1!
b11000 /
1*
#456
0*
#457
b10 :
15
0!
b1 9
b11001 /
1*
#458
0*
#459
b0 :
05
b11010 /
b10 9
18
1*
#460
0*
#461
b0 9
b11011 /
1*
#462
0*
#463
b11100 /
1*
#464
0*
#465
b1 :
1!
b11101 /
1*
#466
0*
#467
0!
b10 :
15
b11110 /
b1 9
b111 $
b111 0
b111 7
1*
#468
0*
#469
b0 :
05
b10 9
b11111 /
08
1*
#470
0*
#471
b100000 /
b0 9
1*
#472
0*
#473
b100001 /
1*
#474
0*
#475
b1 :
1!
b100010 /
1*
#476
0*
#477
b10 :
15
0!
b1 9
b100011 /
1*
#478
0*
#479
b0 :
05
b100100 /
b10 9
18
1*
#480
0*
#481
b0 9
b100101 /
1*
#482
0*
#483
b100110 /
1*
#484
0*
#485
b1 :
1!
b100111 /
1*
#486
0*
#487
0!
b10 :
15
b101000 /
b1 9
b110 $
b110 0
b110 7
1*
#488
0*
#489
b0 :
05
b10 9
b101001 /
08
1*
#490
0*
#491
b101010 /
b0 9
1*
#492
0*
#493
b101011 /
1*
#494
0*
#495
b1 :
1!
b101100 /
1*
#496
0*
#497
b10 :
15
0!
b1 9
b101101 /
1*
#498
0*
#499
b0 :
05
b101110 /
b10 9
18
1*
#500
0*
#501
b0 9
b101111 /
1*
#502
0*
#503
b110000 /
1*
#504
0*
#505
b1 :
1!
b110001 /
1*
#506
0*
#507
b1 >
1,
0!
b10 :
15
b101 .
b0 /
b1 9
b101 $
b101 0
b101 7
1*
#508
0*
#509
b0 :
05
b10 >
13
0,
b10 9
b1 =
b1 /
08
1*
#510
0*
#511
b0 >
03
b10 /
b10 =
b0 9
b111 $
b111 0
b111 7
1*
#512
0*
#513
b0 =
b11 /
1*
#514
0*
#515
b1 :
1!
b100 /
1*
#516
0*
#517
b10 :
15
0!
b1 9
b101 /
1*
#518
0*
#519
b0 :
05
b110 /
b10 9
18
1*
#520
0*
#521
b0 9
b111 /
1*
#522
0*
#523
b1000 /
1*
#524
0*
#525
b1 :
1!
b1001 /
1*
#526
0*
#527
0!
b10 :
15
b1010 /
b1 9
b110 $
b110 0
b110 7
1*
#528
0*
#529
b0 :
05
b10 9
b1011 /
08
1*
#530
0*
#531
b1100 /
b0 9
1*
#532
0*
#533
b1101 /
1*
#534
0*
#535
b1 :
1!
b1110 /
1*
#536
0*
#537
b10 :
15
0!
b1 9
b1111 /
1*
#538
0*
#539
b0 :
05
b10000 /
b10 9
18
1*
#540
0*
#541
b0 9
b10001 /
1*
#542
0*
#543
b10010 /
1*
#544
0*
#545
b1 :
1!
b10011 /
1*
#546
0*
#547
0!
b10 :
15
b10100 /
b1 9
b101 $
b101 0
b101 7
1*
#548
0*
#549
b0 :
05
b10 9
b10101 /
08
1*
#550
0*
#551
b10110 /
b0 9
1*
#552
0*
#553
b10111 /
1*
#554
0*
#555
b1 :
1!
b11000 /
1*
#556
0*
#557
b10 :
15
0!
b1 9
b11001 /
1*
#558
0*
#559
b0 :
05
b11010 /
b10 9
18
1*
#560
0*
#561
b0 9
b11011 /
1*
#562
0*
#563
b11100 /
1*
#564
0*
#565
b1 :
1!
b11101 /
1*
#566
0*
#567
0!
b10 :
15
b11110 /
b1 9
b100 $
b100 0
b100 7
1*
#568
0*
#569
b0 :
05
b10 9
b11111 /
08
1*
#570
0*
#571
b100000 /
b0 9
1*
#572
0*
#573
b100001 /
1*
#574
0*
#575
b1 :
1!
b100010 /
1*
#576
0*
#577
b10 :
15
0!
b1 9
b100011 /
1*
#578
0*
#579
b0 :
05
b100100 /
b10 9
18
1*
#580
0*
#581
b0 9
b100101 /
1*
#582
0*
#583
b100110 /
1*
#584
0*
#585
b1 :
1!
b100111 /
1*
#586
0*
#587
0!
b10 :
15
b101000 /
b1 9
b11 $
b11 0
b11 7
1*
#588
0*
#589
b0 :
05
b10 9
b101001 /
08
1*
#590
0*
#591
b101010 /
b0 9
1*
#592
0*
#593
b101011 /
1*
#594
0*
#595
b1 :
1!
b101100 /
1*
#596
0*
#597
b10 :
15
0!
b1 9
b101101 /
1*
#598
0*
#599
b0 :
05
b101110 /
b10 9
18
1*
#600
0*
#601
b0 9
b101111 /
1*
#602
0*
#603
b110000 /
1*
#604
0*
#605
b1 :
1!
b110001 /
1*
#606
0*
#607
b1 >
1,
0!
b10 :
15
b110 .
b0 /
b1 9
b10 $
b10 0
b10 7
1*
#608
0*
#609
b0 :
05
b10 >
13
0,
b10 9
b1 =
b1 /
08
1*
