Voice_Shifter/voice_corruptor/pulse_gen.sv
module pulse_gen (
    input logic clk,
    input logic flag,
    output logic pulse
);

    typedef enum {IDLE, PULSE, WAIT_LOW} mystate;
    mystate c_state, n_state;

    always_ff @(posedge clk) begin
        c_state <= n_state;
    end

    always_comb begin
        pulse   = 1'b0;
        n_state = c_state;
        case (c_state)
            IDLE: begin
                if (flag)
                    n_state = PULSE;
            end
            PULSE: begin
                pulse = 1'b1;
                n_state = WAIT_LOW;
            end
            WAIT_LOW: begin
                pulse = 1'b0;
                if(!flag)
                    n_state = IDLE;
                else
                    n_state = WAIT_LOW;
            end
        endcase
    end
endmodule

Voice_Shifter/voice_corruptor/updown_counter.sv
module updown_counter #(
    parameter int WIDTH = 8
) (
    input logic clk,
    input logic rst,
    input logic en,
    input logic change,
    input logic [WIDTH-1:0] max_count,
    input logic reload_flag,
    output logic [WIDTH-1:0] count
);

    logic [WIDTH-1:0] counting;
    logic reload;

    pulse_gen reload_pulse (
        .clk(clk),
        .flag(reload_flag),
        .pulse(reload)
    );

    always_ff @(posedge clk or posedge rst) begin
        if(rst)
            counting <= 0;
        else if (change) begin
            if(reload)
                counting <= 0;
            else if(counting == max_count)
                counting <= max_count;
            else
                counting <= counting + en;
        end
        else begin
            if(reload)
                counting <= max_count;
            else if(counting == 0)
                counting <= 0;
            else
                counting <= counting - en;
        end
    end

    assign count = counting;
endmodule

Voice_Shifter/voice_corruptor/down_counter.sv
module down_counter #(
    parameter int WIDTH = 9
)(
    input logic clk,
    input logic rst,
    input logic en,
    input logic reload_flag1,
    input logic reload_flag2,
    input logic [WIDTH-1:0] max_count,
    input logic [WIDTH-1:0] init,
    output logic [WIDTH-1:0] count
);

    logic [WIDTH-1:0] counting;
    logic decrement;
    logic down;
    logic reload1, reload2;

    pulse_gen down_pulse (
        .clk(clk),
        .flag(en),
        .pulse(down)
    );

    pulse_gen reload1_pulse (
        .clk(clk),
        .flag(reload_flag1),
        .pulse(reload1)
    );

    pulse_gen reload2_pulse (
        .clk(clk),
        .flag(reload_flag2),
        .pulse(reload2)
    );

    always_ff @(posedge clk or posedge rst) begin
        if (rst || reload2 || reload1)
            decrement <= 1'b0;
        else if (down)
            decrement <= ~decrement;
    end

    always_ff @(posedge clk or posedge rst) begin
        if (rst || reload2) begin
            counting <= init;
        end else if (reload1) begin
            counting <= max_count;
        end else if (counting == 0)
            counting <= 0;
        else if (en)
            counting <= counting - decrement;
    end


    assign count = counting;

endmodule

Voice_Shifter/voice_corruptor/counter4.sv
module counter4 #(
    parameter int WIDTH = 16
) (
    input  logic             clk,
    input  logic             rst,
    input  logic             en,
    input  logic [WIDTH-1:0] max_count,
    output logic             done
);

    logic [WIDTH-1:0] count;

    always_ff @(posedge clk or posedge rst) begin
        if (rst) begin
            count <= '0;
            done  <= 1'b0;
        end else if (en) begin
            if (count == max_count - 1'b1) begin
                count <= '0;
                done  <= 1'b1;
            end else begin
                count <= count + 1'b1;
                done  <= 1'b0;
            end
        end else begin
            done <= 1'b0;
        end
    end

endmodule

Voice_Shifter/voice_corruptor/KG_controller.sv
module KG_controller (
    input logic clk,
    input logic rst,
    input logic loaded,
    input logic en_loaded,
    input logic [12:0] a,
    output logic [12:0] KA,
    output logic [12:0] KB,
    output logic [12:0] GA,
    output logic [12:0] GB
);

    logic en_2a_counter;
    logic done_2a;
    logic en_KA, en_KB, en_GA, en_GB;
    logic flag_KA, flag_KB, flag_GA, flag_GB;
    logic flag_KA_init, flag_KB_init;
    logic change_GA, change_GB;

    counter4 #(
        .WIDTH(13)
    ) twoa_counter (
        .clk(clk),
        .rst(rst),
        .en(en_2a_counter),
        .max_count(13'd2*a),
        .done(done_2a)
    );

    down_counter #(
        .WIDTH(13)
    ) KA_counter (
        .clk(clk),
        .rst(rst),
        .en(en_KA),
        .reload_flag1(flag_KA),
        .reload_flag2(flag_KA_init),
        .max_count(13'd3*a - 1'b1),
        .init(13'd3*a - 1'b1),
        .count(KA)
    );

    down_counter #(
        .WIDTH(13)
    ) KB_counter (
        .clk(clk),
        .rst(rst),
        .en(en_KB),
        .reload_flag1(flag_KB),
        .reload_flag2(flag_KB_init),
        .max_count(13'd3*a - 1'b1),
        .init(a - 1'b1),
        .count(KB)
    );

    updown_counter #(
        .WIDTH(13)
    ) GA_counter (
        .clk(clk),
        .rst(rst),
        .en(en_GA),
        .change(change_GA),
        .max_count(13'd2*a - 1'b1),
        .reload_flag(flag_GA),
        .count(GA)
    );

    updown_counter #(
        .WIDTH(13)
    ) GB_counter (
        .clk(clk),
        .rst(rst),
        .en(en_GB),
        .change(change_GB),
        .max_count(13'd2*a - 1'b1),
        .reload_flag(flag_GB),
        .count(GB)
    );

    typedef enum {IDLE, RAMP_GA, ONE_GA, RAMP_GB, ONE_GB} mystate;
    mystate c_state, n_state;

    always_ff @(posedge clk or posedge rst) begin
        if (rst) begin
            c_state <= IDLE;
        end else begin
            c_state <= n_state;
        end
    end

    always_comb begin
        case(c_state)
            IDLE: begin
                if(loaded)
                    n_state = RAMP_GA;
                else 
                    n_state= IDLE;
            end
            RAMP_GA: begin
                if(done_2a)
                    n_state = ONE_GA;
                else
                    n_state = RAMP_GA;
            end
            ONE_GA: begin
                if(done_2a)
                    n_state = RAMP_GB;
                else
                    n_state = ONE_GA;
            end
            RAMP_GB: begin
                if(done_2a)
                    n_state = ONE_GB;
                else
                    n_state = RAMP_GB;
            end
            ONE_GB: begin
                if(done_2a)
                    n_state = RAMP_GA;
                else
                    n_state = ONE_GB;
            end
            default: n_state = IDLE;
        endcase
    end

    always_comb begin
        case(c_state)
            IDLE: begin
                en_KA = 1'b0;
                en_KB = 1'b0;
                en_GA = 1'b0;
                en_GB = 1'b0;
                flag_KA = 1'b0;
                flag_KA_init = 1'b0;
                flag_KB = 1'b0;
                flag_KB_init = 1'b0;
                flag_GA = 1'b0;
                flag_GB = 1'b0;
                change_GA = 1'b0;
                change_GB = 1'b0;
                en_2a_counter = 1'b0;
            end
            RAMP_GA: begin
                en_KA = en_loaded;
                en_KB = en_loaded;
                en_GA = en_loaded;
                en_GB = en_loaded;
                flag_KA = 1'b1;
                flag_KA_init = 1'b1;
                flag_KB = 1'b0;
                flag_KB_init = 1'b1;
                flag_GA = 1'b1;
                flag_GB = 1'b1;
                change_GA = 1'b1;
                change_GB = 1'b0;
                en_2a_counter = en_loaded;
            end
            ONE_GA: begin
                en_KA = en_loaded;
                en_KB = en_loaded;
                en_GA = en_loaded;
                en_GB = en_loaded;
                flag_KA = 1'b0;
                flag_KA_init = 1'b0;
                flag_KB = 1'b0;
                flag_KB_init = 1'b0;
                flag_GA = 1'b0;
                flag_GB = 1'b0;
                change_GA = 1'b1;
                change_GB = 1'b0;
                en_2a_counter = en_loaded;
            end
            RAMP_GB: begin
                en_KA = en_loaded;
                en_KB = en_loaded;
                en_GA = en_loaded;
                en_GB = en_loaded;
                flag_KA = 1'b0;
                flag_KA_init = 1'b0;
                flag_KB = 1'b1;
                flag_KB_init = 1'b0;
                flag_GA = 1'b0;
                flag_GB = 1'b0;
                change_GA = 1'b0;
                change_GB = 1'b1;
                en_2a_counter = en_loaded;
            end
            ONE_GB: begin
                en_KA = en_loaded;
                en_KB = en_loaded;
                en_GA = en_loaded;
                en_GB = en_loaded;
                flag_KA = 1'b0;
                flag_KA_init = 1'b0;
                flag_KB = 1'b0;
                flag_KB_init = 1'b0;
                flag_GA = 1'b0;
                flag_GB = 1'b0;
                change_GA = 1'b0;
                change_GB = 1'b1;
                en_2a_counter = en_loaded;
            end
        endcase
    end

endmodule

Voice_Shifter/voice_corruptor/testbenches/KG_controller_tb.sv
module KG_controller_tb;

    localparam int CLOCK_PERIOD = 2;
    localparam int TICK_PER_FRAME = 30;

    logic clk = 1'b0;
    logic rst = 1'b0;
    logic loaded = 1'b0;
    logic en_loaded;
    logic [12:0] a = 13'd128;
    logic [12:0] KA;
    logic [12:0] KB;
    logic [12:0] GA;
    logic [12:0] GB;

    KG_controller uut (
        .clk(clk),
        .rst(rst),
        .loaded(loaded),
        .en_loaded(en_loaded),
        .a(a),
        .KA(KA),
        .KB(KB),
        .GA(GA),
        .GB(GB)
    );

    int tick, frame;

    always #(CLOCK_PERIOD/2) clk = ~clk;

    always @(posedge clk) begin
        if (rst) begin
            tick <= 0;
            frame <= 0;
        end else if (tick == TICK_PER_FRAME - 1) begin
            if(frame == 0)
                loaded <= 1'b1;
            tick <= 0;
            frame <= frame + 1;
        end else begin
            tick <= tick + 1;
        end
    end

    assign en_loaded = (frame >= 1) && ((tick % TICK_PER_FRAME) == TICK_PER_FRAME - 1);
    
    initial begin
        $dumpfile("KG_controller_tb.vcd");
        $dumpvars(0, KG_controller_tb);
        $display("%6s %8s %7s %9s %6s %6s %6s %6s %6s",
                 "time", "state", "loaded", "en_loaded", "KA", "KB", "GA", "GB", "frame");
        $display("%6s %8s %7s %9s %6s %6s %6s %6s %6s",
                 "----", "--------", "------", "---------", "----", "----", "----", "----", "-----");

        rst = 1'b1;
        repeat (4) @(posedge clk);
        @(negedge clk);
        rst = 1'b0;

        wait (frame == 2048);
        @(posedge clk);
        $display("done");
        $finish;
    end

    // Packed bytes so $strobe can print it (Icarus rejects string/$strobe).
    reg [8*8-1:0] state_str;
    always @(*) begin
        case (uut.c_state)
            uut.IDLE:    state_str = "IDLE";
            uut.RAMP_GA: state_str = "RAMP_GA";
            uut.ONE_GA:  state_str = "ONE_GA";
            uut.RAMP_GB: state_str = "RAMP_GB";
            uut.ONE_GB:  state_str = "ONE_GB";
            default:     state_str = "???";
        endcase
    end

    always @(posedge clk) begin
        if ( ( (frame % 128) == 0 || (frame % 128 ) == 1 || (frame % 128 ) == 2) &&
        (tick == 0 || tick == 1 || tick == 2))
            $strobe("%6t %8s %7b %9b %6d %6d %6d %6d %6d",
                    $time, state_str, loaded, en_loaded, KA, KB, GA, GB, frame);
    end
endmodule

Voice_Shifter/voice_corruptor/testbenches/KG_controller_tb.vcd
$date
	Fri Sep  4 13:59:17 2026
$end
$version
	Icarus Verilog
$end
$timescale
	1s
$end
$scope module KG_controller_tb $end
$var wire 1 ! en_loaded $end
$var wire 13 " KB [12:0] $end
$var wire 13 # KA [12:0] $end
$var wire 13 $ GB [12:0] $end
$var wire 13 % GA [12:0] $end
$var parameter 32 & CLOCK_PERIOD $end
$var parameter 32 ' TICK_PER_FRAME $end
$var reg 13 ( a [12:0] $end
$var reg 1 ) clk $end
$var reg 1 * loaded $end
$var reg 1 + rst $end
$var reg 64 , state_str [63:0] $end
$var integer 32 - frame [31:0] $end
$var integer 32 . tick [31:0] $end
$scope module uut $end
$var wire 13 / a [12:0] $end
$var wire 1 ) clk $end
$var wire 1 ! en_loaded $end
$var wire 1 * loaded $end
$var wire 1 + rst $end
$var wire 1 0 done_2a $end
$var wire 13 1 KB [12:0] $end
$var wire 13 2 KA [12:0] $end
$var wire 13 3 GB [12:0] $end
$var wire 13 4 GA [12:0] $end
$var reg 1 5 change_GA $end
$var reg 1 6 change_GB $end
$var reg 1 7 en_2a_counter $end
$var reg 1 8 en_GA $end
$var reg 1 9 en_GB $end
$var reg 1 : en_KA $end
$var reg 1 ; en_KB $end
$var reg 1 < flag_GA $end
$var reg 1 = flag_GB $end
$var reg 1 > flag_KA $end
$var reg 1 ? flag_KA_init $end
$var reg 1 @ flag_KB $end
$var reg 1 A flag_KB_init $end
$var integer 32 B c_state [31:0] $end
$var integer 32 C n_state [31:0] $end
$scope module GA_counter $end
$var wire 1 5 change $end
$var wire 1 ) clk $end
$var wire 13 D count [12:0] $end
$var wire 1 8 en $end
$var wire 13 E max_count [12:0] $end
$var wire 1 < reload_flag $end
$var wire 1 + rst $end
$var wire 1 F reload $end
$var parameter 32 G WIDTH $end
$var reg 13 H counting [12:0] $end
$scope module reload_pulse $end
$var wire 1 ) clk $end
$var wire 1 < flag $end
$var reg 1 F pulse $end
$var integer 32 I c_state [31:0] $end
$var integer 32 J n_state [31:0] $end
$upscope $end
$upscope $end
$scope module GB_counter $end
$var wire 1 6 change $end
$var wire 1 ) clk $end
$var wire 13 K count [12:0] $end
$var wire 1 9 en $end
$var wire 13 L max_count [12:0] $end
$var wire 1 = reload_flag $end
$var wire 1 + rst $end
$var wire 1 M reload $end
$var parameter 32 N WIDTH $end
$var reg 13 O counting [12:0] $end
$scope module reload_pulse $end
$var wire 1 ) clk $end
$var wire 1 = flag $end
$var reg 1 M pulse $end
$var integer 32 P c_state [31:0] $end
$var integer 32 Q n_state [31:0] $end
$upscope $end
$upscope $end
$scope module KA_counter $end
$var wire 1 ) clk $end
$var wire 13 R count [12:0] $end
$var wire 1 : en $end
$var wire 13 S init [12:0] $end
$var wire 13 T max_count [12:0] $end
$var wire 1 > reload_flag1 $end
$var wire 1 ? reload_flag2 $end
$var wire 1 + rst $end
$var wire 1 U reload2 $end
$var wire 1 V reload1 $end
$var wire 1 W down $end
$var parameter 32 X WIDTH $end
$var reg 13 Y counting [12:0] $end
$var reg 1 Z decrement $end
$scope module down_pulse $end
$var wire 1 ) clk $end
$var wire 1 : flag $end
$var reg 1 W pulse $end
$var integer 32 [ c_state [31:0] $end
$var integer 32 \ n_state [31:0] $end
$upscope $end
$scope module reload1_pulse $end
$var wire 1 ) clk $end
$var wire 1 > flag $end
$var reg 1 V pulse $end
$var integer 32 ] c_state [31:0] $end
$var integer 32 ^ n_state [31:0] $end
$upscope $end
$scope module reload2_pulse $end
$var wire 1 ) clk $end
$var wire 1 ? flag $end
$var reg 1 U pulse $end
$var integer 32 _ c_state [31:0] $end
$var integer 32 ` n_state [31:0] $end
$upscope $end
$upscope $end
$scope module KB_counter $end
$var wire 1 ) clk $end
$var wire 13 a count [12:0] $end
$var wire 1 ; en $end
$var wire 13 b init [12:0] $end
$var wire 13 c max_count [12:0] $end
$var wire 1 @ reload_flag1 $end
$var wire 1 A reload_flag2 $end
$var wire 1 + rst $end
$var wire 1 d reload2 $end
$var wire 1 e reload1 $end
$var wire 1 f down $end
$var parameter 32 g WIDTH $end
$var reg 13 h counting [12:0] $end
$var reg 1 i decrement $end
$scope module down_pulse $end
$var wire 1 ) clk $end
$var wire 1 ; flag $end
$var reg 1 f pulse $end
$var integer 32 j c_state [31:0] $end
$var integer 32 k n_state [31:0] $end
$upscope $end
$scope module reload1_pulse $end
$var wire 1 ) clk $end
$var wire 1 @ flag $end
$var reg 1 e pulse $end
$var integer 32 l c_state [31:0] $end
$var integer 32 m n_state [31:0] $end
$upscope $end
$scope module reload2_pulse $end
$var wire 1 ) clk $end
$var wire 1 A flag $end
$var reg 1 d pulse $end
$var integer 32 n c_state [31:0] $end
$var integer 32 o n_state [31:0] $end
$upscope $end
$upscope $end
$scope module twoa_counter $end
$var wire 1 ) clk $end
$var wire 1 7 en $end
$var wire 13 p max_count [12:0] $end
$var wire 1 + rst $end
$var parameter 32 q WIDTH $end
$var reg 13 r count [12:0] $end
$var reg 1 0 done $end
$upscope $end
$upscope $end
$upscope $end
$enddefinitions $end
$comment Show the parameter values. $end
$dumpall
b1101 q
b1101 g
b1101 X
b1101 N
b1101 G
b11110 '
b10 &
$end
#0
$dumpvars
b0 r
b100000000 p
b0 o
b0 n
b0 m
b0 l
b0 k
b0 j
0i
b1111111 h
0f
0e
0d
b101111111 c
b1111111 b
b1111111 a
b0 `
b0 _
b0 ^
b0 ]
b0 \
b0 [
0Z
b101111111 Y
0W
0V
0U
b101111111 T
b101111111 S
b101111111 R
b0 Q
b0 P
b0 O
0M
b11111111 L
b0 K
b0 J
b0 I
b0 H
0F
b11111111 E
b0 D
b0 C
b0 B
0A
0@
0?
0>
0=
0<
0;
0:
09
08
07
06
05
b0 4
b0 3
b101111111 2
b1111111 1
00
b10000000 /
b0 .
b0 -
bx ,
1+
0*
0)
b10000000 (
b0 %
b0 $
b101111111 #
b1111111 "
0!
$end
#1
1)
#2
0)
#3
1)
#4
0)
#5
1)
#6
0)
#7
1)
#8
0+
0)
#9
b1 .
1)
#10
0)
#11
b10 .
1)
#12
0)
#13
b11 .
1)
#14
0)
#15
b100 .
1)
#16
0)
#17
b101 .
1)
#18
0)
#19
b110 .
1)
#20
0)
#21
b111 .
1)
#22
0)
#23
b1000 .
1)
#24
0)
#25
b1001 .
1)
#26
0)
#27
b1010 .
1)
#28
0)
#29
b1011 .
1)
#30
0)
#31
b1100 .
1)
#32
0)
#33
b1101 .
1)
#34
0)
#35
b1110 .
1)
#36
0)
#37
b1111 .
1)
#38
0)
#39
b10000 .
1)
#40
0)
#41
b10001 .
1)
#42
0)
#43
b10010 .
1)
#44
0)
#45
b10011 .
1)
#46
0)
#47
b10100 .
1)
#48
0)
#49
b10101 .
1)
#50
0)
#51
b10110 .
1)
#52
0)
#53
b10111 .
1)
#54
0)
#55
b11000 .
1)
#56
0)
#57
b11001 .
1)
#58
0)
#59
b11010 .
1)
#60
0)
#61
b11011 .
1)
#62
0)
#63
b11100 .
1)
#64
0)
#65
b11101 .
1)
#66
0)
#67
b1 C
b1 -
b0 .
1*
1)
#68
0)
#69
b1 Q
b1 J
b1 o
b1 `
b1 ^
15
1=
1<
1A
1?
1>
b1010010010000010100110101010000010111110100011101000001 ,
b1 .
b1 B
1)
#70
0)
#71
b10 Q
1M
b10 J
1F
b10 o
1d
b10 `
1U
b10 ^
1V
b10 .
b1 P
b1 I
b1 n
b1 _
b1 ]
1)
#72
0)
#73
0V
0U
0d
0F
0M
b10 ]
b10 _
b10 n
b10 I
b10 P
b11 .
b11111111 $
b11111111 3
b11111111 K
b11111111 O
1)
#74
0)
#75
b100 .
1)
#76
0)
#77
b101 .
1)
#78
0)
#79
b110 .
1)
#80
0)
#81
b111 .
1)
#82
0)
#83
b1000 .
1)
#84
0)
#85
b1001 .
1)
#86
0)
#87
b1010 .
1)
#88
0)
#89
b1011 .
1)
#90
0)
#91
b1100 .
1)
#92
0)
#93
b1101 .
1)
#94
0)
#95
b1110 .
1)
#96
0)
#97
b1111 .
1)
#98
0)
#99
b10000 .
1)
#100
0)
#101
b10001 .
1)
#102
0)
#103
b10010 .
1)
#104
0)
#105
b10011 .
1)
#106
0)
#107
b10100 .
1)
#108
0)
#109
b10101 .
1)
#110
0)
#111
b10110 .
1)
#112
0)
#113
b10111 .
1)
#114
0)
#115
b11000 .
1)
#116
0)
#117
b11001 .
1)
#118
0)
#119
b11010 .
1)
#120
0)
#121
b11011 .
1)
#122
0)
#123
b11100 .
1)
#124
0)
#125
b1 k
b1 \
17
19
18
1;
1:
1!
b11101 .
1)
#126
0)
#127
07
09
08
0;
0:
0!
b10 k
1f
b10 \
1W
b10 -
b0 .
b1 j
b1 [
b1 r
b1 %
b1 4
b1 D
b1 H
b11111110 $
b11111110 3
b11111110 K
b11111110 O
1)
#128
0)
#129
b0 \
0W
b0 k
0f
b10 [
b10 j
b1 .
1i
1Z
1)
#130
0)
#131
b10 .
b0 j
b0 [
1)
#132
0)
#133
b11 .
1)
#134
0)
#135
b100 .
1)
#136
0)
#137
b101 .
1)
#138
0)
#139
b110 .
1)
#140
0)
#141
b111 .
1)
#142
0)
#143
b1000 .
1)
#144
0)
#145
b1001 .
1)
#146
0)
#147
b1010 .
1)
#148
0)
#149
b1011 .
1)
#150
0)
#151
b1100 .
1)
#152
0)
#153
b1101 .
1)
#154
0)
#155
b1110 .
1)
#156
0)
#157
b1111 .
1)
#158
0)
#159
b10000 .
1)
#160
0)
#161
b10001 .
1)
#162
0)
#163
b10010 .
1)
#164
0)
#165
b10011 .
1)
#166
0)
#167
b10100 .
1)
#168
0)
#169
b10101 .
1)
#170
0)
#171
b10110 .
1)
#172
0)
#173
b10111 .
1)
#174
0)
#175
b11000 .
1)
#176
0)
#177
b11001 .
1)
#178
0)
#179
b11010 .
1)
#180
0)
#181
b11011 .
1)
#182
0)
#183
b11100 .
1)
#184
0)
#185
b1 k
b1 \
17
19
18
1;
1:
1!
b11101 .
1)
#186
0)
#187
07
09
08
0;
0:
0!
b10 k
1f
b10 \
1W
b11 -
b0 .
b1 j
b1 [
b10 r
b101111110 #
b101111110 2
b101111110 R
b101111110 Y
b1111110 "
b1111110 1
b1111110 a
b1111110 h
b10 %
b10 4
b10 D
b10 H
b11111101 $
b11111101 3
b11111101 K
b11111101 O
1)
#188
0)
#189
b0 \
0W
b0 k
0f
b10 [
b10 j
b1 .
0i
0Z
1)
#190
0)
#191
b10 .
b0 j
b0 [
1)
#192
0)
#193
b11 .
1)
#194
0)
#195
b100 .
1)
#196
0)
#197
b101 .
1)
#198
0)
#199
b110 .
1)
#200
0)
#201
b111 .
1)
#202
0)
#203
b1000 .
1)
#204
0)
#205
b1001 .
1)
#206
0)
#207
b1010 .
1)
#208
0)
#209
b1011 .
1)
#210
0)
#211
b1100 .
1)
#212
0)
#213
b1101 .
1)
#214
0)
#215
b1110 .
1)
#216
0)
#217
b1111 .
1)
#218
0)
#219
b10000 .
1)
#220
0)
#221
b10001 .
1)
#222
0)
#223
b10010 .
1)
#224
0)
#225
b10011 .
1)
#226
0)
#227
b10100 .
1)
#228
0)
#229
b10101 .
1)
#230
0)
#231
b10110 .
1)
#232
0)
#233
b10111 .
1)
#234
0)
#235
b11000 .
1)
#236
0)
#237
b11001 .
1)
#238
0)
#239
b11010 .
1)
#240
0)
#241
b11011 .
1)
#242
0)
#243
b11100 .
1)
#244
0)
#245
b1 k
b1 \
17
19
18
1;
1:
1!
b11101 .
1)
#246
0)
#247
07
09
08
0;
0:
0!
b10 k
1f
b10 \
1W
b100 -
b0 .
b1 j
b1 [
b11 r
b11 %
b11 4
b11 D
b11 H
b11111100 $
b11111100 3
b11111100 K
b11111100 O
1)
#248
0)
#249
b0 \
0W
b0 k
0f
b10 [
b10 j
b1 .
1i
1Z
1)
#250
0)
#251
b10 .
b0 j
b0 [
1)
#252
0)
#253
b11 .
1)
#254
0)
#255
b100 .
1)
#256
0)
#257
b101 .
1)
#258
0)
#259
b110 .
1)
#260
0)
#261
b111 .
1)
#262
0)
#263
b1000 .
1)
#264
0)
#265
b1001 .
1)
#266
0)
#267
b1010 .
1)
#268
0)
#269
b1011 .
1)
#270
0)
#271
b1100 .
1)
#272
0)
#273
b1101 .
1)
#274
0)
#275
b1110 .
1)
#276
0)
#277
b1111 .
1)
#278
0)
#279
b10000 .
1)
#280
0)
#281
b10001 .
1)
#282
0)
#283
b10010 .
1)
#284
0)
#285
b10011 .
1)
#286
0)
#287
b10100 .
1)
#288
0)
#289
b10101 .
1)
#290
0)
#291
b10110 .
1)
#292
0)
#293
b10111 .
1)
#294
0)
#295
b11000 .
1)
#296
0)
#297
b11001 .
1)
#298
0)
#299
b11010 .
1)
#300
0)
#301
b11011 .
1)
#302
0)
#303
b11100 .
1)
#304
0)
#305
b1 k
b1 \
17
19
18
1;
1:
1!
b11101 .
1)
#306
0)
#307
07
09
08
0;
0:
0!
b10 k
1f
b10 \
1W
b101 -
b0 .
b1 j
b1 [
b100 r
b101111101 #
b101111101 2
b101111101 R
b101111101 Y
b1111101 "
b1111101 1
b1111101 a
b1111101 h
b100 %
b100 4
b100 D
b100 H
b11111011 $
b11111011 3
b11111011 K
b11111011 O
1)
#308
0)
#309
b0 \
0W
b0 k
0f
b10 [
b10 j
b1 .
0i
0Z
1)
#310
0)
#311
b10 .
b0 j
b0 [
1)
#312
0)
#313
b11 .
1)
#314
0)
#315
b100 .
1)
#316
0)
#317
b101 .
1)
#318
0)
#319
b110 .
1)
#320
0)
#321
b111 .
1)
#322
0)
#323
b1000 .
1)
#324
0)
#325
b1001 .
1)
#326
0)
#327
b1010 .
1)
#328
0)
#329
b1011 .
1)
#330
0)
#331
b1100 .
1)
#332
0)
#333
b1101 .
1)
#334
0)
#335
b1110 .
1)
#336
0)
#337
b1111 .
1)
#338
0)
#339
b10000 .
1)
#340
0)
#341
b10001 .
1)
#342
0)
#343
b10010 .
1)
#344
0)
#345
b10011 .
1)
#346
0)
#347
b10100 .
1)
#348
0)
#349
b10101 .
1)
#350
0)
#351
b10110 .
1)
#352
0)
#353
b10111 .
1)
#354
0)
#355
b11000 .
1)
#356
0)
#357
b11001 .
1)
#358
0)
#359
b11010 .
1)
#360
0)
#361
b11011 .
1)
#362
0)
#363
b11100 .
1)
#364
0)
#365
b1 k
b1 \
17
19
18
1;
1:
1!
b11101 .
1)
#366
0)
#367
07
09
08
0;
0:
0!
b10 k
1f
b10 \
1W
b110 -
b0 .
b1 j
b1 [
b101 r
b101 %
b101 4
b101 D
b101 H
b11111010 $
b11111010 3
b11111010 K
b11111010 O
1)
#368
0)
#369
b0 \
0W
b0 k
0f
b10 [
b10 j
b1 .
1i
1Z
1)
#370
0)
#371
b10 .
b0 j
b0 [
1)
#372
0)
#373
b11 .
1)
#374
0)
#375
b100 .
1)
#376
0)
#377
b101 .
1)
#378
0)
#379
b110 .
1)
#380
0)
#381
b111 .
1)
#382
0)
#383
b1000 .
1)
#384
0)
#385
b1001 .
1)
#386
0)
#387
b1010 .
1)
#388
0)
#389
b1011 .
1)
#390
0)
#391
b1100 .
1)
#392
0)
#393
b1101 .
1)
#394
0)
#395
b1110 .
1)
#396
0)
#397
b1111 .
1)
#398
0)
#399
b10000 .
1)
#400
0)
#401
b10001 .
1)
#402
0)
#403
b10010 .
1)
#404
0)
#405
b10011 .
1)
#406
0)
#407
b10100 .
1)
#408
0)
#409
b10101 .
1)
#410
0)
#411
b10110 .
1)
#412
0)
#413
b10111 .
1)
#414
0)
#415
b11000 .
1)
#416
0)
#417
b11001 .
1)
#418
0)
#419
b11010 .
1)
#420
0)
#421
b11011 .
1)
#422
0)
#423
b11100 .
1)
#424
0)
#425
b1 k
b1 \
17
19
18
1;
1:
1!
b11101 .
1)
#426
0)
#427
07
09
08
0;
0:
0!
b10 k
1f
b10 \
1W
b111 -
b0 .
b1 j
b1 [
b110 r
b101111100 #
b101111100 2
b101111100 R
b101111100 Y
b1111100 "
b1111100 1
b1111100 a
b1111100 h
b110 %
b110 4
b110 D
b110 H
b11111001 $
b11111001 3
b11111001 K
b11111001 O
1)
#428
0)
#429
b0 \
0W
b0 k
0f
b10 [
b10 j
b1 .
0i
0Z
1)
#430
0)
#431
b10 .
b0 j
b0 [
1)
#432
0)
#433
b11 .
1)
#434
0)
#435
b100 .
1)
#436
0)
#437
b101 .
1)
#438
0)
#439
b110 .
1)
#440
0)
#441
b111 .
1)
#442
0)
#443
b1000 .
1)
#444
0)
#445
b1001 .
1)
#446
0)
#447
b1010 .
1)
#448
0)
#449
b1011 .
1)
#450
0)
#451
b1100 .
1)
#452
0)
#453
b1101 .
1)
#454
0)
#455
b1110 .
1)
#456
0)
#457
b1111 .
1)
#458
0)
#459
b10000 .
1)
#460
0)
#461
b10001 .
1)
#462
0)
#463
b10010 .
1)
#464
0)
#465
b10011 .
1)
#466
0)
#467
b10100 .
1)
#468
0)
#469
b10101 .
1)
#470
0)
#471
b10110 .
1)
#472
0)
#473
b10111 .
1)
#474
0)
#475
b11000 .
1)
#476
0)
#477
b11001 .
1)
#478
0)
#479
b11010 .
1)
#480
0)
#481
b11011 .
1)
#482
0)
#483
b11100 .
1)
#484
0)
#485
b1 k
b1 \
17
19
18
1;
1:
1!
b11101 .
1)
#486
0)
#487
07
09
08
0;
0:
0!
b10 k
1f
b10 \
1W
b1000 -
b0 .
b1 j
b1 [
b111 r
b111 %
b111 4
b111 D
b111 H
b11111000 $
b11111000 3
b11111000 K
b11111000 O
1)
#488
0)
#489
b0 \
0W
b0 k
0f
b10 [
b10 j
b1 .
1i
1Z
1)
#490
0)
#491
b10 .
b0 j
b0 [
1)
#492
0)
#493
b11 .
1)
#494
0)
#495
b100 .
1)
#496
0)
#497
b101 .
1)
#498
0)
#499
b110 .
1)
#500
0)
#501
b111 .
1)
#502
0)
#503
b1000 .
1)
#504
0)
#505
b1001 .
1)
#506
0)
#507
b1010 .
1)
#508
0)
#509
b1011 .
1)
#510
0)
#511
b1100 .
1)
#512
0)
#513
b1101 .
1)
#514
0)
#515
b1110 .
1)
#516
0)
#517
b1111 .
1)
#518
0)
#519
b10000 .
1)
#520
0)
#521
b10001 .
1)
#522
0)
#523
b10010 .
1)
#524
0)
#525
b10011 .
1)
#526
0)
#527
b10100 .
1)
#528
0)
#529
b10101 .
1)
#530
0)
#531
b10110 .
1)
#532
0)
#533
b10111 .
1)
#534
0)
#535
b11000 .
1)
#536
0)
#537
b11001 .
1)
#538
0)
#539
b11010 .
1)
#540
0)
#541
b11011 .
1)
#542
0)
#543
b11100 .
1)
#544
0)
#545
b1 k
b1 \
17
19
18
1;
1:
1!
b11101 .
1)
#546
0)
#547
07
09
08
0;
0:
0!
b10 k
1f
b10 \
1W
b1001 -
b0 .
b1 j
b1 [
b1000 r
b101111011 #
b101111011 2
b101111011 R
b101111011 Y
b1111011 "
b1111011 1
b1111011 a
b1111011 h
b1000 %
b1000 4
b1000 D
b1000 H
b11110111 $
b11110111 3
b11110111 K
b11110111 O
1)
#548
0)
#549
b0 \
0W
b0 k
0f
b10 [
b10 j
b1 .
0i
0Z
1)
#550
0)
#551
b10 .
b0 j
b0 [
1)
#552
0)
#553
b11 .
1)
#554
0)
#555
b100 .
1)
#556
0)
#557
b101 .
1)
#558
0)
#559
b110 .
1)
#560
0)
#561
b111 .
1)
#562
0)
#563
b1000 .
1)
#564
0)
#565
b1001 .
1)
#566
0)
#567
b1010 .
1)
#568
0)
#569
b1011 .
1)
#570
0)
#571
b1100 .
1)
#572
0)
#573
b1101 .
1)
#574
0)
#575
b1110 .
1)
#576
0)
#577
b1111 .
1)
#578
0)
#579
b10000 .
1)
#580
0)
#581
b10001 .
1)
#582
0)
#583
b10010 .
1)
#584
0)
#585
b10011 .
1)
#586
0)
#587
b10100 .
1)
#588
0)
#589
b10101 .
1)
#590
0)
#591
b10110 .
1)
