Voice_Shifter/voice_corruptor/pipeline_div.sv
module pipeline_div #(
    parameter WIDTH = 32
)(
    input logic clk,
    input logic rst,
    input logic [WIDTH-1:0] dividend,
    input logic [WIDTH-1:0] divisor,
    input logic en,
    output logic [WIDTH-1:0] quotient,
    output logic done
);

    logic [4:0] bit_end = WIDTH;
    logic [WIDTH-1:0] div_reg;
    logic [WIDTH-1:0] q_reg = {WIDTH{1'b0}};
    logic [WIDTH-1:0] r_reg = {WIDTH{1'b0}};

    always_comb begin
        if(bit_end == WIDTH)
            div_reg = {{(WIDTH-1){1'b0}}, dividend[WIDTH - 1]};
        else
            div_reg = {r_reg[WIDTH-2:0], dividend[bit_end - 1]};
    end

    always_ff @(posedge clk or posedge rst) begin
        if(rst == 1'b1||!en) 
            bit_end <= WIDTH;
        else if (bit_end > 0)
            bit_end <= bit_end - 1;
        else
            bit_end <= bit_end;
    end 

    always_ff @(posedge clk or posedge rst) begin
        if(rst == 1'b1||!en) begin
            q_reg <= {WIDTH{1'b0}};
            r_reg <= {WIDTH{1'b0}};
        end else if (bit_end == 0) begin
            q_reg <= q_reg;
            r_reg <= r_reg;
        end else if(div_reg >= divisor) begin
            q_reg <= {q_reg[WIDTH-2:0], 1'b1};
            r_reg <= div_reg - divisor;
        end else begin
            q_reg <= {q_reg[WIDTH-2:0], 1'b0};
            r_reg <= div_reg;
        end
    end

    assign quotient = q_reg;
    assign done = (bit_end == 0);

endmodule

Voice_Shifter/voice_corruptor/testbenches/pipeline_div_tb.sv
module pipeline_div_tb;
    localparam int CLK_PERIOD = 2;
    localparam int WIDTH = 14;

    logic clk = 1'b0;
    logic rst = 1'b1;
    logic en = 1'b0;
    logic [WIDTH-1:0] dividend = 14'd1 << 13;
    logic [WIDTH-1:0] divisor  = 14'd255;
    logic [WIDTH-1:0] quotient;
    logic done;

    pipeline_div #(.WIDTH(WIDTH)) uut (
        .clk(clk),
        .rst(rst),
        .en(en),
        .dividend(dividend),
        .divisor(divisor),
        .quotient(quotient),
        .done(done)
    );

    always #(CLK_PERIOD/2) clk = ~clk;

    // Must be at module level — cannot nest always inside initial
    always @(posedge clk) begin
        $display("%0t\t%b\t%b\t%d\t%d\t%d\t%b", $time, rst, en, dividend, divisor, quotient, done);
    end

    initial begin
        $dumpfile("pipeline_div_tb.vcd");
        $dumpvars(0, pipeline_div_tb);

        $display("time\trst\ten\tdividend\tdivisor\tquotient\tdone");
        $display("----\t---\t---\t--------\t--------\t--------\t--------");

        rst = 1'b1;
        repeat (4) @(posedge clk);
        @(negedge clk);
        rst = 1'b0;

        en = 1'b0;
        repeat (4) @(posedge clk);
        @(negedge clk);
        en = 1'b1;

        repeat (50) @(posedge clk);
        $display("done.");
        $finish;
    end
endmodule

Voice_Shifter/voice_corruptor/testbenches/pipeline_div_tb.vcd
$date
	Sun Sep 27 09:04:56 2026
$end
$version
	Icarus Verilog
$end
$timescale
	1s
$end
$scope module pipeline_div_tb $end
$var wire 14 ! quotient [13:0] $end
$var wire 1 " done $end
$var parameter 32 # CLK_PERIOD $end
$var parameter 32 $ WIDTH $end
$var reg 1 % clk $end
$var reg 14 & dividend [13:0] $end
$var reg 14 ' divisor [13:0] $end
$var reg 1 ( en $end
$var reg 1 ) rst $end
$scope module uut $end
$var wire 1 % clk $end
$var wire 14 * dividend [13:0] $end
$var wire 14 + divisor [13:0] $end
$var wire 1 ( en $end
$var wire 14 , quotient [13:0] $end
$var wire 1 ) rst $end
$var wire 1 " done $end
$var parameter 32 - WIDTH $end
$var reg 5 . bit_end [4:0] $end
$var reg 14 / div_reg [13:0] $end
$var reg 14 0 q_reg [13:0] $end
$var reg 14 1 r_reg [13:0] $end
$upscope $end
$upscope $end
$enddefinitions $end
$comment Show the parameter values. $end
$dumpall
b1110 -
b1110 $
b10 #
$end
#0
$dumpvars
b0 1
b0 0
b1 /
b1110 .
b0 ,
b11111111 +
b10000000000000 *
1)
0(
b11111111 '
b10000000000000 &
0%
0"
b0 !
$end
#1
1%
#2
0%
#3
1%
#4
0%
#5
1%
#6
0%
#7
1%
#8
0)
0%
#9
1%
#10
0%
#11
1%
#12
0%
#13
1%
#14
0%
#15
1%
#16
1(
0%
#17
b10 /
b1101 .
b1 1
1%
#18
0%
#19
b100 /
b10 1
b1100 .
1%
#20
0%
#21
b1000 /
b1011 .
b100 1
1%
#22
0%
#23
b10000 /
b1000 1
b1010 .
1%
#24
0%
#25
b100000 /
b1001 .
b10000 1
1%
#26
0%
#27
b1000000 /
b100000 1
b1000 .
1%
#28
0%
#29
b10000000 /
b111 .
b1000000 1
1%
#30
0%
#31
b100000000 /
b10000000 1
b110 .
1%
#32
0%
#33
b10 /
b101 .
b1 1
b1 !
b1 ,
b1 0
1%
#34
0%
#35
b100 /
b10 1
b10 !
b10 ,
b10 0
b100 .
1%
#36
0%
#37
b1000 /
b11 .
b100 1
b100 !
b100 ,
b100 0
1%
#38
0%
#39
b10000 /
b1000 1
b1000 !
b1000 ,
b1000 0
b10 .
1%
#40
0%
#41
b100000 /
b1 .
b10000 1
b10000 !
b10000 ,
b10000 0
1%
#42
0%
#43
b100000x /
1"
b100000 1
b100000 !
b100000 ,
b100000 0
b0 .
1%
