Voice_Shifter/voice_corruptor/pulse_gen.sv
module pulse_gen (
    input logic clk,
    input logic flag,
    output logic pulse
);

    typedef enum {IDLE, PULSE, WAIT_LOW} mystate;
    mystate c_state, n_state;

    always_ff @(posedge clk) begin
        c_state <= n_state;
    end

    always_comb begin
        pulse   = 1'b0;
        n_state = c_state;
        case (c_state)
            IDLE: begin
                if (flag)
                    n_state = PULSE;
            end
            PULSE: begin
                pulse = 1'b1;
                n_state = WAIT_LOW;
            end
            WAIT_LOW: begin
                pulse = 1'b0;
                if(!flag)
                    n_state = IDLE;
                else
                    n_state = WAIT_LOW;
            end
        endcase
    end
endmodule

Voice_Shifter/voice_corruptor/updown_counter.sv
module updown_counter #(
    parameter int WIDTH = 8
) (
    input logic clk,
    input logic rst,
    input logic en,
    input logic change,
    input logic [WIDTH-1:0] max_count,
    input logic reload_flag,
    output logic [WIDTH-1:0] count
);

    logic [WIDTH-1:0] counting;
    logic reload;

    pulse_gen reload_pulse (
        .clk(clk),
        .flag(reload_flag),
        .pulse(reload)
    );

    always_ff @(posedge clk or posedge rst) begin
        if(rst)
            counting <= 0;
        else if (change) begin
            if(reload)
                counting <= 0;
            else if(counting == max_count)
                counting <= max_count;
            else
                counting <= counting + en;
        end
        else begin
            if(reload)
                counting <= max_count;
            else if(counting == 0)
                counting <= 0;
            else
                counting <= counting - en;
        end
    end

    assign count = counting;
endmodule

Voice_Shifter/voice_corruptor/testbenches/updown_counter_tb.sv
module updown_counter_tb;

    localparam int CLK_PERIOD = 2;
    localparam int EN_PERIOD  = 5;    // en high 1 cycle, low 4
    localparam int RELOAD_EVERY = 100; 
    int tick;
    int frame;
    
    localparam int WIDTH = 8;
    logic clk = 1'b0;
    logic rst;
    logic en;
    logic change = 1'b1;
    logic [WIDTH-1:0] max_count = 8'd15;
    logic [WIDTH-1:0] count;
    logic reload_flag;

    updown_counter updown_counter_inst (
        .clk(clk),
        .rst(rst),
        .en(en),
        .change(change),
        .max_count(max_count),
        .reload_flag(reload_flag),
        .count(count)
    );

    always #(CLK_PERIOD/2) clk = ~clk;

    always_ff @(posedge clk) begin
        if (rst) begin
            tick <= 0;
            frame <= 0;
        end else if(tick == RELOAD_EVERY-1) begin
            tick <= 0;
            frame <= frame + 1;
            change <= ~change;
        end else begin
            tick <= tick + 1;
        end 
    end

    assign en = (!rst && ((tick % EN_PERIOD) == EN_PERIOD - 1));
    assign reload_flag = (tick == 0);

    initial begin
        $dumpfile("updown_counter_tb.vcd");
        $dumpvars(0, updown_counter_tb);
        $display("time\trst\ten\tflag\tchange\tcount\tframe\ttick");
        $display("----\t---\t--\t----\t------\t------\t-----\t-----\t----");

        rst = 1'b1;
        repeat (4) @(posedge clk);
        @(negedge clk);
        rst = 1'b0;

        // frame 0 (count), frame 1 (1-tick reload), frame 2 (long flag)
        wait (frame == 4);
        @(posedge clk);
        $display("done.");
        $finish;
    end

    // $strobe prints AFTER nonblocking updates, so count is the new value.
    always @(posedge clk) begin
        if (rst || en || reload_flag )
            $strobe("%0t\t%b\t%b\t%b\t%b\t%0d\t%0d\t%0d",
                    $time, rst, en, reload_flag, change, count, frame, tick);

    end
endmodule

Voice_Shifter/voice_corruptor/testbenches/updown_counter_tb.vcd
$date
	Sat Aug 29 14:21:39 2026
$end
$version
	Icarus Verilog
$end
$timescale
	1s
$end
$scope module updown_counter_tb $end
$var wire 1 ! en $end
$var wire 1 " reload_flag $end
$var wire 8 # count [7:0] $end
$var parameter 32 $ CLK_PERIOD $end
$var parameter 32 % EN_PERIOD $end
$var parameter 32 & RELOAD_EVERY $end
$var parameter 32 ' WIDTH $end
$var reg 1 ( change $end
$var reg 1 ) clk $end
$var reg 8 * max_count [7:0] $end
$var reg 1 + rst $end
$var integer 32 , frame [31:0] $end
$var integer 32 - tick [31:0] $end
$scope module updown_counter_inst $end
$var wire 1 ( change $end
$var wire 1 ) clk $end
$var wire 8 . count [7:0] $end
$var wire 1 ! en $end
$var wire 8 / max_count [7:0] $end
$var wire 1 " reload_flag $end
$var wire 1 + rst $end
$var wire 1 0 reload $end
$var parameter 32 1 WIDTH $end
$var reg 8 2 counting [7:0] $end
$scope module reload_pulse $end
$var wire 1 ) clk $end
$var wire 1 " flag $end
$var reg 1 0 pulse $end
$var integer 32 3 c_state [31:0] $end
$var integer 32 4 n_state [31:0] $end
$upscope $end
$upscope $end
$upscope $end
$enddefinitions $end
$comment Show the parameter values. $end
$dumpall
b1000 1
b1000 '
b1100100 &
b101 %
b10 $
$end
#0
$dumpvars
b1 4
b0 3
b0 2
00
b1111 /
b0 .
b0 -
b0 ,
1+
b1111 *
0)
1(
b0 #
1"
0!
$end
#1
b10 4
10
b1 3
1)
#2
0)
#3
00
b10 3
1)
#4
0)
#5
1)
#6
0)
#7
1)
#8
0+
0)
#9
b0 4
0"
b1 -
1)
#10
0)
#11
b10 -
b0 3
1)
#12
0)
#13
b11 -
1)
#14
0)
#15
1!
b100 -
1)
#16
0)
#17
0!
b101 -
b1 #
b1 .
b1 2
1)
#18
0)
#19
b110 -
1)
#20
0)
#21
b111 -
1)
#22
0)
#23
b1000 -
1)
#24
0)
#25
1!
b1001 -
1)
#26
0)
#27
0!
b1010 -
b10 #
b10 .
b10 2
1)
#28
0)
#29
b1011 -
1)
#30
0)
#31
b1100 -
1)
#32
0)
#33
b1101 -
1)
#34
0)
#35
1!
b1110 -
1)
#36
0)
#37
0!
b1111 -
b11 #
b11 .
b11 2
1)
#38
0)
#39
b10000 -
1)
#40
0)
#41
b10001 -
1)
#42
0)
#43
b10010 -
1)
#44
0)
#45
1!
b10011 -
1)
#46
0)
#47
0!
b10100 -
b100 #
b100 .
b100 2
1)
#48
0)
#49
b10101 -
1)
#50
0)
#51
b10110 -
1)
#52
0)
#53
b10111 -
1)
#54
0)
#55
1!
b11000 -
1)
#56
0)
#57
0!
b11001 -
b101 #
b101 .
b101 2
1)
#58
0)
#59
b11010 -
1)
#60
0)
#61
b11011 -
1)
#62
0)
#63
b11100 -
1)
#64
0)
#65
1!
b11101 -
1)
#66
0)
#67
0!
b11110 -
b110 #
b110 .
b110 2
1)
#68
0)
#69
b11111 -
1)
#70
0)
#71
b100000 -
1)
#72
0)
#73
b100001 -
1)
#74
0)
#75
1!
b100010 -
1)
#76
0)
#77
0!
b100011 -
b111 #
b111 .
b111 2
1)
#78
0)
#79
b100100 -
1)
#80
0)
#81
b100101 -
1)
#82
0)
#83
b100110 -
1)
#84
0)
#85
1!
b100111 -
1)
#86
0)
#87
0!
b101000 -
b1000 #
b1000 .
b1000 2
1)
#88
0)
#89
b101001 -
1)
#90
0)
#91
b101010 -
1)
#92
0)
#93
b101011 -
1)
#94
0)
#95
1!
b101100 -
1)
#96
0)
#97
0!
b101101 -
b1001 #
b1001 .
b1001 2
1)
#98
0)
#99
b101110 -
1)
#100
0)
#101
b101111 -
1)
#102
0)
#103
b110000 -
1)
#104
0)
#105
1!
b110001 -
1)
#106
0)
#107
0!
b110010 -
b1010 #
b1010 .
b1010 2
1)
#108
0)
#109
b110011 -
1)
#110
0)
#111
b110100 -
1)
#112
0)
#113
b110101 -
1)
#114
0)
#115
1!
b110110 -
1)
#116
0)
#117
0!
b110111 -
b1011 #
b1011 .
b1011 2
1)
#118
0)
#119
b111000 -
1)
#120
0)
#121
b111001 -
1)
#122
0)
#123
b111010 -
1)
#124
0)
#125
1!
b111011 -
1)
#126
0)
#127
0!
b111100 -
b1100 #
b1100 .
b1100 2
1)
#128
0)
#129
b111101 -
1)
#130
0)
#131
b111110 -
1)
#132
0)
#133
b111111 -
1)
#134
0)
#135
1!
b1000000 -
1)
#136
0)
#137
0!
b1000001 -
b1101 #
b1101 .
b1101 2
1)
#138
0)
#139
b1000010 -
1)
#140
0)
#141
b1000011 -
1)
#142
0)
#143
b1000100 -
1)
#144
0)
#145
1!
b1000101 -
1)
#146
0)
#147
0!
b1000110 -
b1110 #
b1110 .
b1110 2
1)
#148
0)
#149
b1000111 -
1)
#150
0)
#151
b1001000 -
1)
#152
0)
#153
b1001001 -
1)
#154
0)
#155
1!
b1001010 -
1)
#156
0)
#157
0!
b1001011 -
b1111 #
b1111 .
b1111 2
1)
#158
0)
#159
b1001100 -
1)
#160
0)
#161
b1001101 -
1)
#162
0)
#163
b1001110 -
1)
#164
0)
#165
1!
b1001111 -
1)
#166
0)
#167
0!
b1010000 -
1)
#168
0)
#169
b1010001 -
1)
#170
0)
#171
b1010010 -
1)
#172
0)
#173
b1010011 -
1)
#174
0)
#175
1!
b1010100 -
1)
#176
0)
#177
0!
b1010101 -
1)
#178
0)
#179
b1010110 -
1)
#180
0)
#181
b1010111 -
1)
#182
0)
#183
b1011000 -
1)
#184
0)
#185
1!
b1011001 -
1)
#186
0)
#187
0!
b1011010 -
1)
#188
0)
#189
b1011011 -
1)
#190
0)
#191
b1011100 -
1)
#192
0)
#193
b1011101 -
1)
#194
0)
#195
1!
b1011110 -
1)
#196
0)
#197
0!
b1011111 -
1)
#198
0)
#199
b1100000 -
1)
#200
0)
#201
b1100001 -
1)
#202
0)
#203
b1100010 -
1)
#204
0)
#205
1!
b1100011 -
1)
#206
0)
#207
0!
b1 4
0(
b1 ,
1"
b0 -
1)
#208
0)
#209
b10 4
10
b1 3
0"
b1 -
1)
#210
0)
#211
b0 4
00
b10 -
b10 3
1)
#212
0)
#213
b0 3
b11 -
1)
#214
0)
#215
1!
b100 -
1)
#216
0)
#217
0!
b101 -
b1110 #
b1110 .
b1110 2
1)
#218
0)
#219
b110 -
1)
#220
0)
#221
b111 -
1)
#222
0)
#223
b1000 -
1)
#224
0)
#225
1!
b1001 -
1)
#226
0)
#227
0!
b1010 -
b1101 #
b1101 .
b1101 2
1)
#228
0)
#229
b1011 -
1)
#230
0)
#231
b1100 -
1)
#232
0)
#233
b1101 -
1)
#234
0)
#235
1!
b1110 -
1)
#236
0)
#237
0!
b1111 -
b1100 #
b1100 .
b1100 2
1)
#238
0)
#239
b10000 -
1)
#240
0)
#241
b10001 -
1)
#242
0)
#243
b10010 -
1)
#244
0)
#245
1!
b10011 -
1)
#246
0)
#247
0!
b10100 -
b1011 #
b1011 .
b1011 2
1)
#248
0)
#249
b10101 -
1)
#250
0)
#251
b10110 -
1)
#252
0)
#253
b10111 -
1)
#254
0)
#255
1!
b11000 -
1)
#256
0)
#257
0!
b11001 -
b1010 #
b1010 .
b1010 2
1)
#258
0)
#259
b11010 -
1)
#260
0)
#261
b11011 -
1)
#262
0)
#263
b11100 -
1)
#264
0)
#265
1!
b11101 -
1)
#266
0)
#267
0!
b11110 -
b1001 #
b1001 .
b1001 2
1)
#268
0)
#269
b11111 -
1)
#270
0)
#271
b100000 -
1)
#272
0)
#273
b100001 -
1)
#274
0)
#275
1!
b100010 -
1)
#276
0)
#277
0!
b100011 -
b1000 #
b1000 .
b1000 2
1)
#278
0)
#279
b100100 -
1)
#280
0)
#281
b100101 -
1)
#282
0)
#283
b100110 -
1)
#284
0)
#285
1!
b100111 -
1)
#286
0)
#287
0!
b101000 -
b111 #
b111 .
b111 2
1)
#288
0)
#289
b101001 -
1)
#290
0)
#291
b101010 -
1)
#292
0)
#293
b101011 -
1)
#294
0)
#295
1!
b101100 -
1)
#296
0)
#297
0!
b101101 -
b110 #
b110 .
b110 2
1)
#298
0)
#299
b101110 -
1)
#300
0)
#301
b101111 -
1)
#302
0)
#303
b110000 -
1)
#304
0)
#305
1!
b110001 -
1)
#306
0)
#307
0!
b110010 -
b101 #
b101 .
b101 2
1)
#308
0)
#309
b110011 -
1)
#310
0)
#311
b110100 -
1)
#312
0)
#313
b110101 -
1)
#314
0)
#315
1!
b110110 -
1)
#316
0)
#317
0!
b110111 -
b100 #
b100 .
b100 2
1)
#318
0)
#319
b111000 -
1)
#320
0)
#321
b111001 -
1)
#322
0)
#323
b111010 -
1)
#324
0)
#325
1!
b111011 -
1)
#326
0)
#327
0!
b111100 -
b11 #
b11 .
b11 2
1)
#328
0)
#329
b111101 -
1)
#330
0)
#331
b111110 -
1)
#332
0)
#333
b111111 -
1)
#334
0)
#335
1!
b1000000 -
1)
#336
0)
#337
0!
b1000001 -
b10 #
b10 .
b10 2
1)
#338
0)
#339
b1000010 -
1)
#340
0)
#341
b1000011 -
1)
#342
0)
#343
b1000100 -
1)
#344
0)
#345
1!
b1000101 -
1)
#346
0)
#347
0!
b1000110 -
b1 #
b1 .
b1 2
1)
#348
0)
#349
b1000111 -
1)
#350
0)
#351
b1001000 -
1)
#352
0)
#353
b1001001 -
1)
#354
0)
#355
1!
b1001010 -
1)
#356
0)
#357
0!
b1001011 -
b0 #
b0 .
b0 2
1)
#358
0)
#359
b1001100 -
1)
#360
0)
#361
b1001101 -
1)
#362
0)
#363
b1001110 -
1)
#364
0)
#365
1!
b1001111 -
1)
#366
0)
#367
0!
b1010000 -
1)
#368
0)
#369
b1010001 -
1)
#370
0)
#371
b1010010 -
1)
#372
0)
#373
b1010011 -
1)
#374
0)
#375
1!
b1010100 -
1)
#376
0)
#377
0!
b1010101 -
1)
#378
0)
#379
b1010110 -
1)
#380
0)
#381
b1010111 -
1)
#382
0)
#383
b1011000 -
1)
#384
0)
#385
1!
b1011001 -
1)
#386
0)
#387
0!
b1011010 -
1)
#388
0)
#389
b1011011 -
1)
#390
0)
#391
b1011100 -
1)
#392
0)
#393
b1011101 -
1)
#394
0)
#395
1!
b1011110 -
1)
#396
0)
#397
0!
b1011111 -
1)
#398
0)
#399
b1100000 -
1)
#400
0)
#401
b1100001 -
1)
#402
0)
#403
b1100010 -
1)
#404
0)
#405
1!
b1100011 -
1)
#406
0)
#407
0!
b1 4
1(
b10 ,
1"
b0 -
1)
#408
0)
#409
b10 4
10
b1 3
0"
b1 -
1)
#410
0)
#411
b0 4
00
b10 -
b10 3
1)
#412
0)
#413
b0 3
b11 -
1)
#414
0)
#415
1!
b100 -
1)
#416
0)
#417
0!
b101 -
b1 #
b1 .
b1 2
1)
#418
0)
#419
b110 -
1)
#420
0)
#421
b111 -
1)
#422
0)
#423
b1000 -
1)
#424
0)
#425
1!
b1001 -
1)
#426
0)
#427
0!
b1010 -
b10 #
b10 .
b10 2
1)
#428
0)
#429
b1011 -
1)
#430
0)
#431
b1100 -
1)
#432
0)
#433
b1101 -
1)
#434
0)
#435
1!
b1110 -
1)
#436
0)
#437
0!
b1111 -
b11 #
b11 .
b11 2
1)
#438
0)
#439
b10000 -
1)
#440
0)
#441
b10001 -
1)
#442
0)
#443
b10010 -
1)
#444
0)
#445
1!
b10011 -
1)
#446
0)
#447
0!
b10100 -
b100 #
b100 .
b100 2
1)
#448
0)
#449
b10101 -
1)
#450
0)
#451
b10110 -
1)
#452
0)
#453
b10111 -
1)
#454
0)
#455
1!
b11000 -
1)
#456
0)
#457
0!
b11001 -
b101 #
b101 .
b101 2
1)
#458
0)
#459
b11010 -
1)
#460
0)
#461
b11011 -
1)
#462
0)
#463
b11100 -
1)
#464
0)
#465
1!
b11101 -
1)
#466
0)
#467
0!
b11110 -
b110 #
b110 .
b110 2
1)
#468
0)
#469
b11111 -
1)
#470
0)
#471
b100000 -
1)
#472
0)
#473
b100001 -
1)
#474
0)
#475
1!
b100010 -
1)
#476
0)
#477
0!
b100011 -
b111 #
b111 .
b111 2
1)
#478
0)
#479
b100100 -
1)
#480
0)
#481
b100101 -
1)
#482
0)
#483
b100110 -
1)
#484
0)
#485
1!
b100111 -
1)
#486
0)
#487
0!
b101000 -
b1000 #
b1000 .
b1000 2
1)
#488
0)
#489
b101001 -
1)
#490
0)
#491
b101010 -
1)
#492
0)
#493
b101011 -
1)
#494
0)
#495
1!
b101100 -
1)
#496
0)
#497
0!
b101101 -
b1001 #
b1001 .
b1001 2
1)
#498
0)
#499
b101110 -
1)
#500
0)
#501
b101111 -
1)
#502
0)
#503
b110000 -
1)
#504
0)
#505
1!
b110001 -
1)
#506
0)
#507
0!
b110010 -
b1010 #
b1010 .
b1010 2
1)
#508
0)
#509
b110011 -
1)
#510
0)
#511
b110100 -
1)
#512
0)
#513
b110101 -
1)
#514
0)
#515
1!
b110110 -
1)
#516
0)
#517
0!
b110111 -
b1011 #
b1011 .
b1011 2
1)
#518
0)
#519
b111000 -
1)
#520
0)
#521
b111001 -
1)
#522
0)
#523
b111010 -
1)
#524
0)
#525
1!
b111011 -
1)
#526
0)
#527
0!
b111100 -
b1100 #
b1100 .
b1100 2
1)
#528
0)
#529
b111101 -
1)
#530
0)
#531
b111110 -
1)
#532
0)
#533
b111111 -
1)
#534
0)
#535
1!
b1000000 -
1)
#536
0)
#537
0!
b1000001 -
b1101 #
b1101 .
b1101 2
1)
#538
0)
#539
b1000010 -
1)
#540
0)
#541
b1000011 -
1)
#542
0)
#543
b1000100 -
1)
#544
0)
#545
1!
b1000101 -
1)
#546
0)
#547
0!
b1000110 -
b1110 #
b1110 .
b1110 2
1)
#548
0)
#549
b1000111 -
1)
#550
0)
#551
b1001000 -
1)
#552
0)
#553
b1001001 -
1)
#554
0)
#555
1!
b1001010 -
1)
#556
0)
#557
0!
b1001011 -
b1111 #
b1111 .
b1111 2
1)
#558
0)
#559
b1001100 -
1)
#560
0)
#561
b1001101 -
1)
#562
0)
#563
b1001110 -
1)
#564
0)
#565
1!
b1001111 -
1)
#566
0)
#567
0!
b1010000 -
1)
#568
0)
#569
b1010001 -
1)
#570
0)
#571
b1010010 -
1)
#572
0)
#573
b1010011 -
1)
#574
0)
#575
1!
b1010100 -
1)
#576
0)
#577
0!
b1010101 -
1)
#578
0)
#579
b1010110 -
1)
#580
0)
#581
b1010111 -
1)
#582
0)
#583
b1011000 -
1)
#584
0)
#585
1!
b1011001 -
1)
#586
0)
#587
0!
b1011010 -
1)
#588
0)
#589
b1011011 -
1)
#590
0)
#591
b1011100 -
1)
#592
0)
#593
b1011101 -
1)
#594
0)
#595
1!
b1011110 -
1)
#596
0)
#597
0!
b1011111 -
1)
#598
0)
#599
b1100000 -
1)
#600
0)
#601
b1100001 -
1)
#602
0)
#603
b1100010 -
1)
#604
0)
#605
1!
b1100011 -
1)
#606
0)
#607
0!
b1 4
0(
b11 ,
1"
b0 -
1)
#608
0)
#609
b10 4
10
b1 3
0"
b1 -
1)
#610
0)
#611
b0 4
00
b10 -
b10 3
1)
#612
0)
#613
b0 3
b11 -
1)
#614
0)
#615
1!
b100 -
1)
#616
0)
#617
0!
b101 -
b1110 #
b1110 .
b1110 2
1)
#618
0)
#619
b110 -
1)
#620
0)
#621
b111 -
1)
#622
0)
#623
b1000 -
1)
#624
0)
#625
1!
b1001 -
1)
#626
0)
#627
0!
b1010 -
b1101 #
b1101 .
b1101 2
1)
#628
0)
#629
b1011 -
1)
#630
0)
#631
b1100 -
1)
#632
0)
#633
b1101 -
1)
#634
0)
#635
1!
b1110 -
1)
#636
0)
#637
0!
b1111 -
b1100 #
b1100 .
b1100 2
1)
#638
0)
#639
b10000 -
1)
#640
0)
#641
b10001 -
1)
#642
0)
#643
b10010 -
1)
#644
0)
#645
1!
b10011 -
1)
#646
0)
#647
0!
b10100 -
b1011 #
b1011 .
b1011 2
1)
#648
0)
#649
b10101 -
1)
#650
0)
#651
b10110 -
1)
#652
0)
#653
b10111 -
1)
#654
0)
#655
1!
b11000 -
1)
#656
0)
#657
0!
b11001 -
b1010 #
b1010 .
b1010 2
1)
#658
0)
#659
b11010 -
1)
#660
0)
#661
b11011 -
1)
#662
0)
#663
b11100 -
1)
#664
0)
#665
1!
b11101 -
1)
#666
0)
#667
0!
b11110 -
b1001 #
b1001 .
b1001 2
1)
#668
0)
#669
b11111 -
1)
#670
0)
#671
b100000 -
1)
#672
0)
#673
b100001 -
1)
#674
0)
#675
1!
b100010 -
1)
#676
0)
#677
0!
b100011 -
b1000 #
b1000 .
b1000 2
1)
#678
0)
#679
b100100 -
1)
#680
0)
#681
b100101 -
1)
#682
0)
#683
b100110 -
1)
#684
0)
#685
1!
b100111 -
1)
#686
0)
#687
0!
b101000 -
b111 #
b111 .
b111 2
1)
#688
0)
#689
b101001 -
1)
#690
0)
#691
b101010 -
1)
#692
0)
#693
b101011 -
1)
#694
0)
#695
1!
b101100 -
1)
#696
0)
#697
0!
b101101 -
b110 #
b110 .
b110 2
1)
#698
0)
#699
b101110 -
1)
#700
0)
#701
b101111 -
1)
#702
0)
#703
b110000 -
1)
#704
0)
#705
1!
b110001 -
1)
#706
0)
#707
0!
b110010 -
b101 #
b101 .
b101 2
1)
#708
0)
#709
b110011 -
1)
#710
0)
#711
b110100 -
1)
#712
0)
#713
b110101 -
1)
#714
0)
#715
1!
b110110 -
1)
#716
0)
#717
0!
b110111 -
b100 #
b100 .
b100 2
1)
#718
0)
#719
b111000 -
1)
#720
0)
#721
b111001 -
1)
#722
0)
#723
b111010 -
1)
#724
0)
#725
1!
b111011 -
1)
#726
0)
#727
0!
b111100 -
b11 #
b11 .
b11 2
1)
#728
0)
#729
b111101 -
1)
#730
0)
#731
b111110 -
1)
#732
0)
#733
b111111 -
1)
#734
0)
#735
1!
b1000000 -
1)
#736
0)
#737
0!
b1000001 -
b10 #
b10 .
b10 2
1)
#738
0)
#739
b1000010 -
1)
#740
0)
#741
b1000011 -
1)
#742
0)
#743
b1000100 -
1)
#744
0)
#745
1!
b1000101 -
1)
#746
0)
#747
0!
b1000110 -
b1 #
b1 .
b1 2
1)
#748
0)
#749
b1000111 -
1)
#750
0)
#751
b1001000 -
1)
#752
0)
#753
b1001001 -
1)
#754
0)
#755
1!
b1001010 -
1)
#756
0)
#757
0!
b1001011 -
b0 #
b0 .
b0 2
1)
#758
0)
#759
b1001100 -
1)
#760
0)
#761
b1001101 -
1)
#762
0)
#763
b1001110 -
1)
#764
0)
#765
1!
b1001111 -
1)
#766
0)
#767
0!
b1010000 -
1)
#768
0)
#769
b1010001 -
1)
#770
0)
#771
b1010010 -
1)
#772
0)
#773
b1010011 -
1)
#774
0)
#775
1!
b1010100 -
1)
#776
0)
#777
0!
b1010101 -
1)
#778
0)
#779
b1010110 -
1)
#780
0)
#781
b1010111 -
1)
#782
0)
#783
b1011000 -
1)
#784
0)
#785
1!
b1011001 -
1)
#786
0)
#787
0!
b1011010 -
1)
#788
0)
#789
b1011011 -
1)
#790
0)
#791
b1011100 -
1)
#792
0)
#793
b1011101 -
1)
#794
0)
#795
1!
b1011110 -
1)
#796
0)
#797
0!
b1011111 -
1)
#798
0)
#799
b1100000 -
1)
#800
0)
#801
b1100001 -
1)
#802
0)
#803
b1100010 -
1)
#804
0)
#805
1!
b1100011 -
1)
#806
0)
#807
0!
b1 4
1(
b100 ,
1"
b0 -
1)
#808
0)
#809
b10 4
10
b1 3
0"
b1 -
1)
